Metadata-Version: 2.1
Name: html5validate
Version: 0.0.2
Summary: Pure Python Basic HTML validatation library - for CI, django tests, etc.  Based on HTML5lib
Home-page: https://github.com/danthedeckie/html5validate
Author: Daniel Fairhead
Author-email: danthedeckie@gmail.com
License: UNKNOWN
Download-URL: https://github.com/danthedeckie/html5validate/tarball/0.0.2
Keywords: html5,validation,web,lint
Platform: UNKNOWN
Classifier: Development Status :: 4 - Beta
Classifier: Intended Audience :: Developers
Classifier: License :: OSI Approved :: MIT License
Classifier: Topic :: Software Development :: Libraries :: Python Modules
Classifier: Programming Language :: Python
